diform/__init__.py
diform-0.0.1.dist-info/METADATA
diform-0.0.1.dist-info/WHEEL
diform-0.0.1.dist-info/licenses/LICENSE
diform-0.0.1.dist-info/RECORD
